hellodemo123/__init__.py
hellodemo123/hello.py
hellodemo123/data/test.txt
hellodemo123-0.1.0.dist-info/METADATA
hellodemo123-0.1.0.dist-info/WHEEL
hellodemo123-0.1.0.dist-info/top_level.txt
hellodemo123-0.1.0.dist-info/RECORD
