Metadata-Version: 2.1
Name: hellodemo123
Version: 0.1.0
Summary: A brief description of the package
Author: ZhangKaifang
Author-email: devinzhang1994@163.com
License: apache 3.0
Classifier: Development Status :: 3 - Alpha
Classifier: Intended Audience :: Developers
Classifier: License :: OSI Approved :: MIT License
Classifier: Programming Language :: Python :: 3
Classifier: Programming Language :: Python :: 3.6
Classifier: Programming Language :: Python :: 3.7
Classifier: Programming Language :: Python :: 3.8
Requires-Python: >=3.6
